python_updict-0.1.2.dist-info/DESCRIPTION.rst
python_updict-0.1.2.dist-info/METADATA
python_updict-0.1.2.dist-info/metadata.json
python_updict-0.1.2.dist-info/RECORD
python_updict-0.1.2.dist-info/top_level.txt
python_updict-0.1.2.dist-info/WHEEL
updict/__init__.py
updict/exceptions.py
updict/updict.py
