Metadata-Version: 2.0
Name: python-updict
Version: 0.1.2
Summary: Update Python dictionaries
Home-page: https://github.com/AndrewIngram/python-updict
Author: Andrew Ingram
Author-email: andy@andrewingram.net
License: BSD
Keywords: python-updict
Platform: UNKNOWN
Classifier: Development Status :: 2 - Pre-Alpha
Classifier: Intended Audience :: Developers
Classifier: License :: OSI Approved :: BSD License
Classifier: Natural Language :: English
Classifier: Programming Language :: Python :: 2
Classifier: Programming Language :: Python :: 2.6
Classifier: Programming Language :: Python :: 2.7
Classifier: Programming Language :: Python :: 3
Classifier: Programming Language :: Python :: 3.3
Classifier: Programming Language :: Python :: 3.4
